flask_help_tools/__init__.py
flask_help_tools/check_and_run_module.py
flask_help_tools/module1.py
flask_help_tools/module2.py
flask_help_tools/module3.py
flask_help_tools/module4.py
flask_help_tools/module5.py
flask_help_tools/module6.py
flask_help_tools/module7.py
flask_help_tools/module8.py
flask_help_tools/module9.py
flask_help_tools-0.3.5.dist-info/LICENSE
flask_help_tools-0.3.5.dist-info/METADATA
flask_help_tools-0.3.5.dist-info/WHEEL
flask_help_tools-0.3.5.dist-info/top_level.txt
flask_help_tools-0.3.5.dist-info/RECORD
