Metadata-Version: 2.1
Name: flask-help-tools
Version: 0.3.5
Summary: A library that provides examples and solutions for common tasks in Flask applications
Home-page: https://github.com/rathe12/flask-help-tools
Author: rathe12
Author-email: markzerone1@gmail.com
License: UNKNOWN
Platform: UNKNOWN
Classifier: Programming Language :: Python :: 3
Classifier: License :: OSI Approved :: MIT License
Classifier: Operating System :: OS Independent
Requires-Python: >=3.6
License-File: LICENSE
Requires-Dist: Flask >=1.1.2
